bprinter/__init__.py
bprinter/ascii_art.py
bprinter/constants.py
bprinter/exceptions.py
bprinter/formatting.py
bprinter/platform.py
bprinter/printer.py
bprinter/styles.py
bprinter-0.2.0.dist-info/LICENSE
bprinter-0.2.0.dist-info/METADATA
bprinter-0.2.0.dist-info/WHEEL
bprinter-0.2.0.dist-info/entry_points.txt
bprinter-0.2.0.dist-info/top_level.txt
bprinter-0.2.0.dist-info/RECORD
