Metadata-Version: 2.2
Name: bprinter
Version: 0.2.0
Summary: A powerful cross-platform terminal styling library
Home-page: https://github.com/DGaliaf/bprinter
Author: DGaliaf
Project-URL: Bug Tracker, https://github.com/DGaliaf/bprinter/issues
Project-URL: Documentation, https://github.com/DGaliaf/bprinter
Project-URL: Source Code, https://github.com/DGaliaf/bprinter
Keywords: terminal cli ansi-colors text-formatting ascii-art cross-platform console terminal-colors styling markdown logging
Classifier: Development Status :: 4 - Beta
Classifier: Intended Audience :: Developers
Classifier: Topic :: Software Development :: Libraries :: Python Modules
Classifier: Topic :: Terminals
Classifier: Topic :: Text Processing
Classifier: Programming Language :: Python :: 3
Classifier: Programming Language :: Python :: 3.7
Classifier: Programming Language :: Python :: 3.8
Classifier: Programming Language :: Python :: 3.9
Classifier: Programming Language :: Python :: 3.10
Classifier: Programming Language :: Python :: 3.11
Classifier: License :: OSI Approved :: MIT License
Classifier: Operating System :: OS Independent
Classifier: Environment :: Console
Requires-Python: >=3.7
License-File: LICENSE
Requires-Dist: pyfiglet>=1.0.2
Requires-Dist: moonitoring==0.1.0
Dynamic: author
Dynamic: classifier
Dynamic: description
Dynamic: description-content-type
Dynamic: home-page
Dynamic: keywords
Dynamic: project-url
Dynamic: requires-dist
Dynamic: requires-python
Dynamic: summary
